nccapy/__init__.py
nccapy/Geo/BaseMesh.py
nccapy/Geo/BaseMesh.pyi
nccapy/Geo/Obj.py
nccapy/Geo/Obj.pyi
nccapy/Geo/__init__.py
nccapy/Image/Canvas.py
nccapy/Image/Image.py
nccapy/Image/RGBA.py
nccapy/Image/__init__.py
nccapy/Math/Mat2.py
nccapy/Math/Mat3.py
nccapy/Math/Mat3.pyi
nccapy/Math/Mat4.py
nccapy/Math/Mat4.pyi
nccapy/Math/Quaternion.py
nccapy/Math/Transform.py
nccapy/Math/Transform.pyi
nccapy/Math/Util.py
nccapy/Math/Util.pyi
nccapy/Math/Vec2.py
nccapy/Math/Vec2.pyi
nccapy/Math/Vec3.py
nccapy/Math/Vec3.pyi
nccapy/Math/Vec4.py
nccapy/Math/Vec4.pyi
nccapy/Math/__init__.py
nccapy/Math/__init__.pyi
nccapy-0.1.7.dist-info/METADATA
nccapy-0.1.7.dist-info/WHEEL
nccapy-0.1.7.dist-info/licenses/LICENSE.txt
nccapy-0.1.7.dist-info/RECORD
