Metadata-Version: 2.4
Name: nccapy
Version: 0.1.7
Summary: nccapy is a python package use for teaching graphics at the NCCA
Project-URL: Homepage, https://github.com/NCCA/nccapy
Project-URL: Issues, https://github.com/NCCA/nccapy/issues
Author-email: Jon Macey <jmacey@bournemouth.ac.uk>
License: Copyright 2024 Jon Macey
License-File: LICENSE.txt
Classifier: Operating System :: OS Independent
Classifier: Programming Language :: Python :: 3
Requires-Python: >=3.10
Requires-Dist: numpy
Requires-Dist: pillow
Requires-Dist: pygame
Provides-Extra: build
Requires-Dist: build; extra == 'build'
Requires-Dist: hatchling; extra == 'build'
Provides-Extra: codegen
Requires-Dist: numpy; extra == 'codegen'
Requires-Dist: pytest; extra == 'codegen'
Requires-Dist: ruff; extra == 'codegen'
Provides-Extra: lint
Requires-Dist: pre-commit; extra == 'lint'
Requires-Dist: ruff; extra == 'lint'
Provides-Extra: tests
Requires-Dist: coverage; extra == 'tests'
Requires-Dist: numpy; extra == 'tests'
Requires-Dist: pillow; extra == 'tests'
Requires-Dist: pygame; extra == 'tests'
Requires-Dist: pytest; extra == 'tests'
Requires-Dist: pytest-cov; extra == 'tests'
